{
  "optimization_metadata": {
    "timestamp": "20251204_205615",
    "data_period": "2010-09-01 to 2024-12-31",
    "total_trading_days": 3740,
    "strategies_tested": 4
  },
  "strategy_results": {
    "sentiment_momentum": {
      "metadata": {
        "total_combinations_tested": 12600,
        "combinations_with_trades": 0
      },
      "best_results": {
        "best_sharpe": null,
        "best_return": null,
        "best_calmar": null,
        "most_trades": null
      },
      "top_10_results": []
    },
    "volume_reversal": {
      "metadata": {
        "total_combinations_tested": 19200,
        "combinations_with_trades": 0
      },
      "best_results": {
        "best_sharpe": null,
        "best_return": null,
        "best_calmar": null,
        "most_trades": null
      },
      "top_10_results": []
    },
    "risk_adjusted_bollinger": {
      "metadata": {
        "total_combinations_tested": 36864,
        "combinations_with_trades": 0
      },
      "best_results": {
        "best_sharpe": null,
        "best_return": null,
        "best_calmar": null,
        "most_trades": null
      },
      "top_10_results": []
    },
    "time_decay_momentum": {
      "metadata": {
        "total_combinations_tested": 14400,
        "combinations_with_trades": 0
      },
      "best_results": {
        "best_sharpe": null,
        "best_return": null,
        "best_calmar": null,
        "most_trades": null
      },
      "top_10_results": []
    }
  }
}