{
  "version": "1",
  "metadata": {
    "marimo_version": "0.18.2"
  },
  "cells": [
    {
      "id": "vblA",
      "code_hash": "6e4d34ef469e54a57d947782335a753c",
      "outputs": [
        {
          "type": "data",
          "data": {
            "text/plain": ""
          }
        }
      ],
      "console": []
    },
    {
      "id": "bkHC",
      "code_hash": "2de19edaae37059dfe662da6e1f86b49",
      "outputs": [
        {
          "type": "data",
          "data": {
            "text/plain": ""
          }
        }
      ],
      "console": []
    },
    {
      "id": "lEQa",
      "code_hash": "85605c23af025ba0e5142742587be484",
      "outputs": [
        {
          "type": "data",
          "data": {
            "text/plain": ""
          }
        }
      ],
      "console": []
    },
    {
      "id": "PKri",
      "code_hash": "7adfba2ac8495779f1bdeb7b309e2f7d",
      "outputs": [
        {
          "type": "data",
          "data": {
            "text/plain": ""
          }
        }
      ],
      "console": []
    },
    {
      "id": "Xref",
      "code_hash": "b3d8587115b7176ecf84579dbb5f43e3",
      "outputs": [
        {
          "type": "data",
          "data": {
            "text/plain": ""
          }
        }
      ],
      "console": []
    },
    {
      "id": "SFPL",
      "code_hash": "b643ea06e83662cb4b01398ccad58daf",
      "outputs": [
        {
          "type": "data",
          "data": {
            "text/plain": ""
          }
        }
      ],
      "console": []
    },
    {
      "id": "BYtC",
      "code_hash": "26e77a4eecc4cfcf9c0f7c657920d72d",
      "outputs": [
        {
          "type": "data",
          "data": {
            "text/plain": ""
          }
        }
      ],
      "console": []
    },
    {
      "id": "Hbol",
      "code_hash": null,
      "outputs": [
        {
          "type": "data",
          "data": {
            "text/plain": ""
          }
        }
      ],
      "console": []
    },
    {
      "id": "MJUe",
      "code_hash": null,
      "outputs": [
        {
          "type": "data",
          "data": {
            "text/plain": ""
          }
        }
      ],
      "console": []
    }
  ]
}