{
  "annotations": {
    "list": [
      {
        "builtIn": 1,
        "datasource": "-- Grafana --",
        "enable": true,
        "hide": true,
        "iconColor": "rgba(0, 211, 255, 1)",
        "name": "Annotations & Alerts",
        "type": "dashboard"
      }
    ]
  },
  "editable": true,
  "gnetId": null,
  "graphTooltip": 0,
  "id": null,
  "links": [],
  "panels": [
    {
      "aliasColors": {},
      "bars": false,
      "dashLength": 10,
      "dashes": false,
      "datasource": "Prometheus",
      "fill": 1,
      "fillGradient": 0,
      "gridPos": {
        "h": 9,
        "w": 12,
        "x": 0,
        "y": 0
      },
      "hiddenSeries": false,
      "id": 2,
      "legend": {
        "avg": false,
        "current": false,
        "max": false,
        "min": false,
        "show": true,
        "total": false,
        "values": false
      },
      "lines": true,
      "linewidth": 1,
      "nullPointMode": "null",
      "options": {
        "dataLinks": []
      },
      "percentage": false,
      "pointradius": 2,
      "points": false,
      "renderer": "flot",
      "seriesOverrides": [],
      "spaceLength": 10,
      "stack": false,
      "steppedLine": false,
      "targets": [
        {
          "expr": "sum(rate(http_requests_total{job=\"cbsc-services\"}[5m])) by (kubernetes_name)",
          "legendFormat": "{{kubernetes_name}}",
          "refId": "A"
        }
      ],
      "thresholds": [],
      "timeFrom": null,
      "timeRegions": [],
      "timeShift": null,
      "title": "Request Rate",
      "tooltip": {
        "shared": true,
        "sort": 0,
        "value_type": "individual"
      },
      "type": "graph",
      "xaxis": {
        "buckets": null,
        "mode": "time",
        "name": null,
        "show": true,
        "values": []
      },
      "yaxes": [
        {
          "format": "reqps",
          "label": null,
          "logBase": 1,
          "max": null,
          "min": null,
          "show": true
        },
        {
          "format": "short",
          "label": null,
          "logBase": 1,
          "max": null,
          "min": null,
          "show": true
        }
      ],
      "yaxis": {
        "align": false,
        "alignLevel": null
      }
    },
    {
      "aliasColors": {},
      "bars": false,
      "dashLength": 10,
      "dashes": false,
      "datasource": "Prometheus",
      "fill": 1,
      "fillGradient": 0,
      "gridPos": {
        "h": 9,
        "w": 12,
        "x": 12,
        "y": 0
      },
      "hiddenSeries": false,
      "id": 3,
      "legend": {
        "avg": false,
        "current": false,
        "max": false,
        "min": false,
        "show": true,
        "total": false,
        "values": false
      },
      "lines": true,
      "linewidth": 1,
      "nullPointMode": "null",
      "options": {
        "dataLinks": []
      },
      "percentage": false,
      "pointradius": 2,
      "points": false,
      "renderer": "flot",
      "seriesOverrides": [
        {
          "alias": "/5xx/",
          "color": "#F2495C"
        },
        {
          "alias": "/4xx/",
          "color": "#FF9830"
        }
      ],
      "spaceLength": 10,
      "stack": false,
      "steppedLine": false,
      "targets": [
        {
          "expr": "sum(rate(http_requests_total{job=\"cbsc-services\",status=~\"4..\"}[5m])) by (kubernetes_name)",
          "legendFormat": "{{kubernetes_name}} 4xx",
          "refId": "A"
        },
        {
          "expr": "sum(rate(http_requests_total{job=\"cbsc-services\",status=~\"5..\"}[5m])) by (kubernetes_name)",
          "legendFormat": "{{kubernetes_name}} 5xx",
          "refId": "B"
        }
      ],
      "thresholds": [],
      "timeFrom": null,
      "timeRegions": [],
      "timeShift": null,
      "title": "Error Rate",
      "tooltip": {
        "shared": true,
        "sort": 0,
        "value_type": "individual"
      },
      "type": "graph",
      "xaxis": {
        "buckets": null,
        "mode": "time",
        "name": null,
        "show": true,
        "values": []
      },
      "yaxes": [
        {
          "format": "reqps",
          "label": null,
          "logBase": 1,
          "max": null,
          "min": null,
          "show": true
        },
        {
          "format": "short",
          "label": null,
          "logBase": 1,
          "max": null,
          "min": null,
          "show": true
        }
      ],
      "yaxis": {
        "align": false,
        "alignLevel": null
      }
    },
    {
      "datasource": "Prometheus",
      "fieldConfig": {
        "defaults": {
          "custom": {},
          "mappings": [],
          "thresholds": {
            "mode": "absolute",
            "steps": [
              {
                "color": "green",
                "value": null
              },
              {
                "color": "red",
                "value": 80
              }
            ]
          }
        },
        "overrides": []
      },
      "gridPos": {
        "h": 8,
        "w": 4,
        "x": 0,
        "y": 9
      },
      "id": 4,
      "options": {
        "colorMode": "value",
        "graphMode": "area",
        "justifyMode": "auto",
        "orientation": "auto",
        "reduceOptions": {
          "calcs": [
            "lastNotNull"
          ],
          "fields": "",
          "values": false
        },
        "textMode": "auto"
      },
      "pluginVersion": "7.5.7",
      "targets": [
        {
          "expr": "sum(cbsc_service_status{service=~\"frontend|api-gateway|user-management|strategy-dashboard|quant-system|config-service\"})",
          "legendFormat": "",
          "refId": "A"
        }
      ],
      "title": "Healthy Services",
      "type": "stat"
    },
    {
      "datasource": "Prometheus",
      "fieldConfig": {
        "defaults": {
          "custom": {},
          "mappings": [],
          "thresholds": {
            "mode": "absolute",
            "steps": [
              {
                "color": "green",
                "value": null
              },
              {
                "color": "red",
                "value": 80
              }
            ]
          },
          "unit": "ms"
        },
        "overrides": []
      },
      "gridPos": {
        "h": 8,
        "w": 4,
        "x": 4,
        "y": 9
      },
      "id": 5,
      "options": {
        "colorMode": "value",
        "graphMode": "area",
        "justifyMode": "auto",
        "orientation": "auto",
        "reduceOptions": {
          "calcs": [
            "lastNotNull"
          ],
          "fields": "",
          "values": false
        },
        "textMode": "auto"
      },
      "pluginVersion": "7.5.7",
      "targets": [
        {
          "expr": "avg(cbsc_service_response_seconds{service=~\"frontend|api-gateway|user-management|strategy-dashboard|quant-system|config-service\"})",
          "legendFormat": "",
          "refId": "A"
        }
      ],
      "title": "Avg Response Time",
      "type": "stat"
    },
    {
      "datasource": "Prometheus",
      "fieldConfig": {
        "defaults": {
          "custom": {},
          "mappings": [],
          "thresholds": {
            "mode": "absolute",
            "steps": [
              {
                "color": "green",
                "value": null
              },
              {
                "color": "red",
                "value": 80
              }
            ]
          },
          "unit": "none"
        },
        "overrides": []
      },
      "gridPos": {
        "h": 8,
        "w": 4,
        "x": 8,
        "y": 9
      },
      "id": 6,
      "options": {
        "colorMode": "value",
        "graphMode": "area",
        "justifyMode": "auto",
        "orientation": "auto",
        "reduceOptions": {
          "calcs": [
            "lastNotNull"
          ],
          "fields": "",
          "values": false
        },
        "textMode": "auto"
      },
      "pluginVersion": "7.5.7",
      "targets": [
        {
          "expr": "cbsc_postgres_connections",
          "legendFormat": "",
          "refId": "A"
        }
      ],
      "title": "PostgreSQL Connections",
      "type": "stat"
    },
    {
      "datasource": "Prometheus",
      "fieldConfig": {
        "defaults": {
          "custom": {},
          "mappings": [],
          "thresholds": {
            "mode": "absolute",
            "steps": [
              {
                "color": "green",
                "value": null
              },
              {
                "color": "red",
                "value": 80
              }
            ]
          },
          "unit": "decbytes"
        },
        "overrides": []
      },
      "gridPos": {
        "h": 8,
        "w": 4,
        "x": 12,
        "y": 9
      },
      "id": 7,
      "options": {
        "colorMode": "value",
        "graphMode": "area",
        "justifyMode": "auto",
        "orientation": "auto",
        "reduceOptions": {
          "calcs": [
            "lastNotNull"
          ],
          "fields": "",
          "values": false
        },
        "textMode": "auto"
      },
      "pluginVersion": "7.5.7",
      "targets": [
        {
          "expr": "redis_memory_used_bytes",
          "legendFormat": "",
          "refId": "A"
        }
      ],
      "title": "Redis Memory Usage",
      "type": "stat"
    },
    {
      "aliasColors": {},
      "bars": false,
      "dashLength": 10,
      "dashes": false,
      "datasource": "Prometheus",
      "fill": 1,
      "fillGradient": 0,
      "gridPos": {
        "h": 9,
        "w": 12,
        "x": 0,
        "y": 17
      },
      "hiddenSeries": false,
      "id": 8,
      "legend": {
        "avg": false,
        "current": false,
        "max": false,
        "min": false,
        "show": true,
        "total": false,
        "values": false
      },
      "lines": true,
      "linewidth": 1,
      "nullPointMode": "null",
      "options": {
        "dataLinks": []
      },
      "percentage": false,
      "pointradius": 2,
      "points": false,
      "renderer": "flot",
      "seriesOverrides": [],
      "spaceLength": 10,
      "stack": false,
      "steppedLine": false,
      "targets": [
        {
          "expr": "histogram_quantile(0.50, rate(http_request_duration_seconds_bucket{job=\"cbsc-services\"}[5m]))",
          "legendFormat": "50th percentile",
          "refId": "A"
        },
        {
          "expr": "histogram_quantile(0.95, rate(http_request_duration_seconds_bucket{job=\"cbsc-services\"}[5m]))",
          "legendFormat": "95th percentile",
          "refId": "B"
        },
        {
          "expr": "histogram_quantile(0.99, rate(http_request_duration_seconds_bucket{job=\"cbsc-services\"}[5m]))",
          "legendFormat": "99th percentile",
          "refId": "C"
        }
      ],
      "thresholds": [],
      "timeFrom": null,
      "timeRegions": [],
      "timeShift": null,
      "title": "Response Time Percentiles",
      "tooltip": {
        "shared": true,
        "sort": 0,
        "value_type": "individual"
      },
      "type": "graph",
      "xaxis": {
        "buckets": null,
        "mode": "time",
        "name": null,
        "show": true,
        "values": []
      },
      "yaxes": [
        {
          "format": "s",
          "label": null,
          "logBase": 1,
          "max": null,
          "min": null,
          "show": true
        },
        {
          "format": "short",
          "label": null,
          "logBase": 1,
          "max": null,
          "min": null,
          "show": true
        }
      ],
      "yaxis": {
        "align": false,
        "alignLevel": null
      }
    },
    {
      "aliasColors": {},
      "bars": false,
      "dashLength": 10,
      "dashes": false,
      "datasource": "Prometheus",
      "fill": 1,
      "fillGradient": 0,
      "gridPos": {
        "h": 9,
        "w": 12,
        "x": 12,
        "y": 17
      },
      "hiddenSeries": false,
      "id": 9,
      "legend": {
        "avg": false,
        "current": false,
        "max": false,
        "min": false,
        "show": true,
        "total": false,
        "values": false
      },
      "lines": true,
      "linewidth": 1,
      "nullPointMode": "null",
      "options": {
        "dataLinks": []
      },
      "percentage": false,
      "pointradius": 2,
      "points": false,
      "renderer": "flot",
      "seriesOverrides": [],
      "spaceLength": 10,
      "stack": false,
      "steppedLine": false,
      "targets": [
        {
          "expr": "sum(rate(strategy_executions_total[5m])) by (status)",
          "legendFormat": "{{status}}",
          "refId": "A"
        }
      ],
      "thresholds": [],
      "timeFrom": null,
      "timeRegions": [],
      "timeShift": null,
      "title": "Strategy Executions",
      "tooltip": {
        "shared": true,
        "sort": 0,
        "value_type": "individual"
      },
      "type": "graph",
      "xaxis": {
        "buckets": null,
        "mode": "time",
        "name": null,
        "show": true,
        "values": []
      },
      "yaxes": [
        {
          "format": "reqps",
          "label": null,
          "logBase": 1,
          "max": null,
          "min": null,
          "show": true
        },
        {
          "format": "short",
          "label": null,
          "logBase": 1,
          "max": null,
          "min": null,
          "show": true
        }
      ],
      "yaxis": {
        "align": false,
        "alignLevel": null
      }
    }
  ],
  "refresh": "5s",
  "schemaVersion": 27,
  "style": "dark",
  "tags": [
    "cbsc",
    "overview"
  ],
  "templating": {
    "list": []
  },
  "time": {
    "from": "now-1h",
    "to": "now"
  },
  "timepicker": {},
  "timezone": "",
  "title": "CBSC System Overview",
  "uid": "cbsc-overview",
  "version": 1
}